jwpo/__init__.py
jwpo/__main__.py
jwpo-1.0.4.dist-info/LICENSE
jwpo-1.0.4.dist-info/METADATA
jwpo-1.0.4.dist-info/WHEEL
jwpo-1.0.4.dist-info/top_level.txt
jwpo-1.0.4.dist-info/RECORD
